ptCrypt/__init__.py
ptCrypt/Asymmetric/DSA.py
ptCrypt/Asymmetric/RSA.py
ptCrypt/Asymmetric/__init__.py
ptCrypt/Asymmetric/ECC/Curve.py
ptCrypt/Asymmetric/ECC/__init__.py
ptCrypt/Attacks/DSA.py
ptCrypt/Attacks/RSA.py
ptCrypt/Attacks/__init__.py
ptCrypt/Attacks/Symmetric/__init__.py
ptCrypt/Attacks/Symmetric/CBC/CbcPkcs7PaddingOracleAttack.py
ptCrypt/Attacks/Symmetric/CBC/__init__.py
ptCrypt/Attacks/Symmetric/ECB/EcbEncryptionOracleAppendAttack.py
ptCrypt/Attacks/Symmetric/ECB/__init__.py
ptCrypt/Attacks/Symmetric/RC4/FluhrerMantinShamirAttack.py
ptCrypt/Attacks/Symmetric/RC4/__init__.py
ptCrypt/Math/__init__.py
ptCrypt/Math/base.py
ptCrypt/Math/primality.py
ptCrypt/Math/smallPrimes.py
ptCrypt/Symmetric/AES.py
ptCrypt/Symmetric/BlockCipher.py
ptCrypt/Symmetric/Cipher.py
ptCrypt/Symmetric/RC4.py
ptCrypt/Symmetric/__init__.py
ptCrypt/Symmetric/Modes/CBC.py
ptCrypt/Symmetric/Modes/ECB.py
ptCrypt/Symmetric/Modes/Mode.py
ptCrypt/Symmetric/Modes/__init__.py
ptCrypt/Symmetric/Paddings/PKCS5Padding.py
ptCrypt/Symmetric/Paddings/Padding.py
ptCrypt/Symmetric/Paddings/ZeroPadding.py
ptCrypt/Symmetric/Paddings/__init__.py
ptCrypt/Util/__init__.py
ptCrypt/Util/keys.py
ptCrypt-0.0.14.1.dist-info/LICENSE
ptCrypt-0.0.14.1.dist-info/METADATA
ptCrypt-0.0.14.1.dist-info/WHEEL
ptCrypt-0.0.14.1.dist-info/top_level.txt
ptCrypt-0.0.14.1.dist-info/RECORD
