Metadata-Version: 2.1
Name: ptCrypt
Version: 0.0.14.1
Summary: Cryptographic and cryptography related algorithms implemented with pure Python
Home-page: https://github.com/0awawa0/ptCrypt
Author: awawa
Author-email: mail.0awawa0@gmail.com
License: UNKNOWN
Keywords: Cryptography
Platform: UNKNOWN
License-File: LICENSE
